fpxpy/JSONSpanExporter.py
fpxpy/__init__.py
fpxpy/capturePrint.py
fpxpy/logger.py
fpxpy/measure.py
fpxpy/py.typed
fpxpy/routes.py
fpxpy/test_tracing.py
fpxpy/tracing.py
fpxpy/utils.py
fpxpy-0.3.5.dist-info/METADATA
fpxpy-0.3.5.dist-info/WHEEL
fpxpy-0.3.5.dist-info/RECORD
