Metadata-Version: 2.4
Name: fpxpy
Version: 0.3.5
Summary: Fiberplane studio integration with FastAPI
Project-URL: Homepage, https://github.com/fiberplane/fpx
Project-URL: Issues, https://github.com/fiberplane/fpx/issues
Author-email: Fiberplane <support@fiberplane.com>, mellowagain <py@mari.zip>, flenter <flenter@users.noreply.github.com>
Classifier: License :: OSI Approved :: MIT License
Classifier: Operating System :: OS Independent
Classifier: Programming Language :: Python :: 3
Requires-Python: >=3.10
Requires-Dist: dataclasses-json>=0.6.7
Requires-Dist: fastapi>=0.108.0
Requires-Dist: opentelemetry-api>=1.29.0
Requires-Dist: opentelemetry-exporter-otlp>=1.29.0
Requires-Dist: opentelemetry-instrumentation-fastapi>=0.50b0
Requires-Dist: opentelemetry-sdk>=1.29.0
Requires-Dist: requests>=2.32.3
Requires-Dist: tracing>=0.1.3
Requires-Dist: types-requests>=2.32.0.20241016
